{
    "remarks": "01%2BEdgetunnel%F0%9F%94%AE%40Surfboardv2ray",
    "log": {
        "access": "",
        "error": "",
        "loglevel": "warning"
    },
    "outbounds": [
        {
            "tag": "proxy",
            "protocol": "vless",
            "settings": {
                "vnext": [
                    {
                        "address": "crackthecode.ftp.sh",
                        "port": 443,
                        "users": [
                            {
                                "id": "5ab76485-f6b9-4340-8be2-260bc8510cb0",
                                "alterId": 0,
                                "email": "t@t.tt",
                                "security": "auto",
                                "encryption": "none",
                                "flow": ""
                            }
                        ]
                    }
                ]
            },
            "streamSettings": {
                "network": "ws",
                "wsSettings": {
                    "path": "",
                    "headers": {
                        "Host": "ecp.cushingreflex1.workers.dev"
                    }
                },
                "security": "tls",
                "tlsSettings": {
                    "allowInsecure": true,
                    "serverName": "ecp.cushingreflex1.workers.dev",
                    "alpn": [],
                    "show": false
                },
                "sockopt": {
                    "dialerProxy": "fragment",
                    "tcpKeepAliveIdle": 100,
                    "tcpNoDelay": true
                }
            },
            "mux": {
                "enabled": false,
                "concurrency": -1
            }
        },
        {
            "tag": "fragment",
            "protocol": "freedom",
            "settings": {
                "domainStrategy": "AsIs",
                "fragment": {
                    "packets": "tlshello",
                    "length": "1-5",
                    "interval": "1-5"
                }
            },
            "streamSettings": {
                "sockopt": {
                    "tcpKeepAliveIdle": 100,
                    "tcpNoDelay": true
                }
            }
        },
        {
            "tag": "direct",
            "protocol": "freedom",
            "settings": {}
        },
        {
            "tag": "block",
            "protocol": "blackhole",
            "settings": {
                "response": {
                    "type": "http"
                }
            }
        }
    ],
    "inbounds": [
        {
            "tag": "socks",
            "port": 10808,
            "listen": "127.0.0.1",
            "protocol": "socks",
            "sniffing": {
                "enabled": true,
                "destOverride": [
                    "http",
                    "tls"
                ],
                "routeOnly": false
            },
            "settings": {
                "auth": "noauth",
                "udp": true,
                "allowTransparent": false
            }
        },
        {
            "tag": "http",
            "port": 10809,
            "listen": "127.0.0.1",
            "protocol": "http",
            "sniffing": {
                "enabled": true,
                "destOverride": [
                    "http",
                    "tls"
                ],
                "routeOnly": false
            },
            "settings": {
                "auth": "noauth",
                "udp": true,
                "allowTransparent": false
            }
        }
    ]
}